<?xml version="1.0" encoding="utf-8"?>
<xliff xmlns="urn:oasis:names:tc:xliff:document:1.2" xmlns:xsi="http://www.w3.org/2001/XMLSchema-instance" version="1.2" xsi:schemaLocation="urn:oasis:names:tc:xliff:document:1.2 xliff-core-1.2-transitional.xsd">
  <file datatype="xml" original="ComDefaultInterfaceAttribute.xml" source-language="en-US" target-language="zh-TW">
    <header>
      <tool tool-id="mdxliff" tool-name="mdxliff" tool-version="1.0-15c36f0" tool-company="Microsoft" />
      <xliffext:skl_file_name xmlns:xliffext="urn:microsoft:content:schema:xliffextensions">02cd5861-7ce2-4a82-b358-31f8435a0ac5bebc42de10d622a6ca4cf15e8b73574d9ead1018.skl</xliffext:skl_file_name>
      <xliffext:version xmlns:xliffext="urn:microsoft:content:schema:xliffextensions">1.2</xliffext:version>
      <xliffext:ms.openlocfilehash xmlns:xliffext="urn:microsoft:content:schema:xliffextensions">bebc42de10d622a6ca4cf15e8b73574d9ead1018</xliffext:ms.openlocfilehash>
      <xliffext:ms.sourcegitcommit xmlns:xliffext="urn:microsoft:content:schema:xliffextensions">d31dc2ede16f6f7bc64e90d9f897ff54c4e3869b</xliffext:ms.sourcegitcommit>
      <xliffext:ms.lasthandoff xmlns:xliffext="urn:microsoft:content:schema:xliffextensions">04/03/2018</xliffext:ms.lasthandoff>
      <xliffext:moniker_ids xmlns:xliffext="urn:microsoft:content:schema:xliffextensions">netcore-1.0,netcore-1.1,netcore-2.0,netcore-2.1,netframework-4.5.1,netframework-4.5.2,netframework-4.5,netframework-4.6.1,netframework-4.6.2,netframework-4.6,netframework-4.7.1,netframework-4.7,netstandard-1.1,netstandard-1.2,netstandard-1.3,netstandard-1.4,netstandard-1.5,netstandard-1.6,netstandard-2.0,xamarinandroid-7.1,xamarinios-10.8,xamarinmac-3.0</xliffext:moniker_ids>
    </header>
    <body>
      <group id="content" extype="content">
        <trans-unit id="101" translate="yes" xml:space="preserve" uid="T:System.Runtime.InteropServices.ComDefaultInterfaceAttribute">
          <source>Specifies a default interface to expose to COM.</source>
          <target state="translated">指定要公開 (Expose) 至 COM 的預設介面。</target>       </trans-unit>
        <trans-unit id="102" translate="yes" xml:space="preserve" uid="T:System.Runtime.InteropServices.ComDefaultInterfaceAttribute">
          <source>This class cannot be inherited.</source>
          <target state="translated">這個類別無法被繼承。</target>       </trans-unit>
        <trans-unit id="103" translate="yes" xml:space="preserve" extradata="MT" uid="T:System.Runtime.InteropServices.ComDefaultInterfaceAttribute">
          <source>Compilers do not necessarily respect the order in which interfaces are implemented.</source>
          <target state="translated">編譯器不一定受影響的順序介面實作。</target>       </trans-unit>
        <trans-unit id="104" translate="yes" xml:space="preserve" extradata="MT" uid="T:System.Runtime.InteropServices.ComDefaultInterfaceAttribute">
          <source>For example, suppose you have the following code:</source>
          <target state="translated">例如，假設您有下列的程式碼：</target>       </trans-unit>
        <trans-unit id="105" translate="yes" xml:space="preserve" extradata="MT" uid="T:System.Runtime.InteropServices.ComDefaultInterfaceAttribute">
          <source>The compiler emits the implemented interfaces as <ph id="ph1">`IDerived, IBase`</ph>.</source>
          <target state="translated">編譯器會發出做為實作的介面<ph id="ph1">`IDerived, IBase`</ph>。</target>       </trans-unit>
        <trans-unit id="106" translate="yes" xml:space="preserve" extradata="MT" uid="T:System.Runtime.InteropServices.ComDefaultInterfaceAttribute">
          <source>The ordering of interfaces is important  when using the <ph id="ph1">&lt;xref:System.Runtime.InteropServices.ClassInterfaceAttribute&gt;</ph> class with <ph id="ph2">`[ClassInterface(ClassInterfaceType.None)]`</ph> to expose an explicit interface as the default interface.</source>
          <target state="translated">介面的順序很重要，使用時<ph id="ph1">&lt;xref:System.Runtime.InteropServices.ClassInterfaceAttribute&gt;</ph>類別<ph id="ph2">`[ClassInterface(ClassInterfaceType.None)]`</ph>公開明確的介面的預設介面。</target>       </trans-unit>
        <trans-unit id="107" translate="yes" xml:space="preserve" extradata="MT" uid="T:System.Runtime.InteropServices.ComDefaultInterfaceAttribute">
          <source>Regardless of the specified <ph id="ph1">`ClassInterfaceType`</ph>, use the <ph id="ph2">&lt;xref:System.Runtime.InteropServices.ComDefaultInterfaceAttribute&gt;</ph> attribute to specify which interface should be recognized as the default.</source>
          <target state="translated">不論指定<ph id="ph1">`ClassInterfaceType`</ph>，使用<ph id="ph2">&lt;xref:System.Runtime.InteropServices.ComDefaultInterfaceAttribute&gt;</ph>屬性來指定哪個介面應該辨識為預設值。</target>       </trans-unit>
        <trans-unit id="108" translate="yes" xml:space="preserve" extradata="MT" uid="T:System.Runtime.InteropServices.ComDefaultInterfaceAttribute">
          <source>Note that the type decorated by the <ph id="ph1">&lt;xref:System.Runtime.InteropServices.ComDefaultInterfaceAttribute&gt;</ph> must actually derive from the interface specified as the default interface.</source>
          <target state="translated">請注意，型別裝飾的<ph id="ph1">&lt;xref:System.Runtime.InteropServices.ComDefaultInterfaceAttribute&gt;</ph>實際上必須衍生自指定的預設介面的介面。</target>       </trans-unit>
        <trans-unit id="109" translate="yes" xml:space="preserve" uid="M:System.Runtime.InteropServices.ComDefaultInterfaceAttribute.#ctor(System.Type)">
          <source>A <ph id="ph1">&lt;see cref="T:System.Type" /&gt;</ph> value indicating the default interface to expose to COM.</source>
          <target state="translated"><ph id="ph1">&lt;see cref="T:System.Type" /&gt;</ph> 值，表示要公開至 COM 的預設介面。</target>       </trans-unit>
        <trans-unit id="110" translate="yes" xml:space="preserve" uid="M:System.Runtime.InteropServices.ComDefaultInterfaceAttribute.#ctor(System.Type)">
          <source>Initializes a new instance of the <ph id="ph1">&lt;see cref="T:System.Runtime.InteropServices.ComDefaultInterfaceAttribute" /&gt;</ph> class with the specified <ph id="ph2">&lt;see cref="T:System.Type" /&gt;</ph> object as the default interface exposed to COM.</source>
          <target state="translated">使用指定的 <ph id="ph1">&lt;see cref="T:System.Runtime.InteropServices.ComDefaultInterfaceAttribute" /&gt;</ph> 物件做為公開至 COM 的預設介面，初始化 <ph id="ph2">&lt;see cref="T:System.Type" /&gt;</ph> 類別的新執行個體。</target>       </trans-unit>
        <trans-unit id="111" translate="yes" xml:space="preserve" extradata="MT" uid="M:System.Runtime.InteropServices.ComDefaultInterfaceAttribute.#ctor(System.Type)">
          <source>The <ph id="ph1">`defaultInterface`</ph> type passed to the constructor must be visible to COM.</source>
          <target state="translated"><ph id="ph1">`defaultInterface`</ph>傳遞至建構函式的類型必須為 COM 可見。</target>       </trans-unit>
        <trans-unit id="112" translate="yes" xml:space="preserve" uid="P:System.Runtime.InteropServices.ComDefaultInterfaceAttribute.Value">
          <source>Gets the <ph id="ph1">&lt;see cref="T:System.Type" /&gt;</ph> object that specifies the default interface to expose to COM.</source>
          <target state="translated">取得 <ph id="ph1">&lt;see cref="T:System.Type" /&gt;</ph> 物件，其指定要公開至 COM 的預設介面。</target>       </trans-unit>
        <trans-unit id="113" translate="yes" xml:space="preserve" extradata="MT" uid="P:System.Runtime.InteropServices.ComDefaultInterfaceAttribute.Value">
          <source>The <ph id="ph1">&lt;see cref="T:System.Type" /&gt;</ph> object that specifies the default interface to expose to COM.</source>
          <target state="translated"><ph id="ph1">&lt;see cref="T:System.Type" /&gt;</ph> 物件，其指定要公開至 COM 的預設介面。</target>       </trans-unit>
      </group>
    </body>
  </file>
</xliff>