<?xml version="1.0" encoding="utf-8"?>
<xliff xmlns="urn:oasis:names:tc:xliff:document:1.2" xmlns:xsi="http://www.w3.org/2001/XMLSchema-instance" version="1.2" xsi:schemaLocation="urn:oasis:names:tc:xliff:document:1.2 xliff-core-1.2-transitional.xsd">
  <file datatype="xml" original="LoggerVerbosity.xml" source-language="en-US" target-language="zh-TW">
    <header>
      <tool tool-id="mdxliff" tool-name="mdxliff" tool-version="1.0-15c36f0" tool-company="Microsoft" />
      <xliffext:skl_file_name xmlns:xliffext="urn:microsoft:content:schema:xliffextensions">02cd5861-7ce2-4a82-b358-31f8435a0ac5f8b1c30fd9fa972987cbf9f67a0e73a0bf689d9c.skl</xliffext:skl_file_name>
      <xliffext:version xmlns:xliffext="urn:microsoft:content:schema:xliffextensions">1.2</xliffext:version>
      <xliffext:ms.openlocfilehash xmlns:xliffext="urn:microsoft:content:schema:xliffextensions">f8b1c30fd9fa972987cbf9f67a0e73a0bf689d9c</xliffext:ms.openlocfilehash>
      <xliffext:ms.sourcegitcommit xmlns:xliffext="urn:microsoft:content:schema:xliffextensions">d31dc2ede16f6f7bc64e90d9f897ff54c4e3869b</xliffext:ms.sourcegitcommit>
      <xliffext:ms.lasthandoff xmlns:xliffext="urn:microsoft:content:schema:xliffextensions">04/03/2018</xliffext:ms.lasthandoff>
      <xliffext:moniker_ids xmlns:xliffext="urn:microsoft:content:schema:xliffextensions">netframework-4.5.1,netframework-4.5.2,netframework-4.5,netframework-4.6.1,netframework-4.6.2,netframework-4.6,netframework-4.7.1,netframework-4.7</xliffext:moniker_ids>
    </header>
    <body>
      <group id="content" extype="content">
        <trans-unit id="101" translate="yes" xml:space="preserve" uid="T:Microsoft.Build.Framework.LoggerVerbosity">
          <source>Specifies the available verbosity levels of a <ph id="ph1">&lt;see cref="T:Microsoft.Build.Utilities.Logger" /&gt;</ph>.</source>
          <target state="translated">指定 <ph id="ph1">&lt;see cref="T:Microsoft.Build.Utilities.Logger" /&gt;</ph> 的可用詳細等級。</target>       </trans-unit>
        <trans-unit id="102" translate="yes" xml:space="preserve" extradata="MT" uid="T:Microsoft.Build.Framework.LoggerVerbosity">
          <source>The descriptions of verbosity levels are only guidelines to how a typical logger (including the default <ph id="ph1">[!INCLUDE[vstecmsbuild](~/includes/vstecmsbuild-md.md)]</ph> console logger) logs build events.</source>
          <target state="translated">是唯一的指導方針，以詳細資訊層級的說明如何一般記錄器 (包括預設<ph id="ph1">[!INCLUDE[vstecmsbuild](~/includes/vstecmsbuild-md.md)]</ph>主控台記錄器) 記錄建置事件。</target>       </trans-unit>
        <trans-unit id="103" translate="yes" xml:space="preserve" extradata="MT" uid="T:Microsoft.Build.Framework.LoggerVerbosity">
          <source>Loggers are free to interpret verbosity levels in any way they want.</source>
          <target state="translated">記錄器可以用來解譯任何他們想要的方式的詳細資訊層級。</target>       </trans-unit>
        <trans-unit id="104" translate="yes" xml:space="preserve" extradata="MT" uid="T:Microsoft.Build.Framework.LoggerVerbosity">
          <source>The following example shows how to write a basic logger that responds to build events.</source>
          <target state="translated">下列範例會示範如何撰寫基本記錄器回應建置事件。</target>       </trans-unit>
        <trans-unit id="105" translate="yes" xml:space="preserve" uid="F:Microsoft.Build.Framework.LoggerVerbosity.Detailed">
          <source>Detailed verbosity, which displays errors, warnings, messages with <ph id="ph1">&lt;see cref="T:Microsoft.Build.Framework.MessageImportance" /&gt;</ph> values of <ph id="ph2">&lt;see cref="F:Microsoft.Build.Framework.MessageImportance.High" /&gt;</ph> or <ph id="ph3">&lt;see cref="F:Microsoft.Build.Framework.MessageImportance.Normal" /&gt;</ph>, all status events, and a build summary.</source>
          <target state="translated">詳細等級，顯示錯誤、警告、<ph id="ph1">&lt;see cref="T:Microsoft.Build.Framework.MessageImportance" /&gt;</ph> 值為 <ph id="ph2">&lt;see cref="F:Microsoft.Build.Framework.MessageImportance.High" /&gt;</ph> 或 <ph id="ph3">&lt;see cref="F:Microsoft.Build.Framework.MessageImportance.Normal" /&gt;</ph> 的訊息、所有狀態事件，以及建置摘要。</target>       </trans-unit>
        <trans-unit id="106" translate="yes" xml:space="preserve" uid="F:Microsoft.Build.Framework.LoggerVerbosity.Diagnostic">
          <source>Diagnostic verbosity, which displays all errors, warnings, messages, status events, and a build summary.</source>
          <target state="translated">診斷詳細等級，顯示所有錯誤、警告、訊息、狀態事件，以及建置摘要。</target>       </trans-unit>
        <trans-unit id="107" translate="yes" xml:space="preserve" uid="F:Microsoft.Build.Framework.LoggerVerbosity.Minimal">
          <source>Minimal verbosity, which displays errors, warnings, messages with <ph id="ph1">&lt;see cref="T:Microsoft.Build.Framework.MessageImportance" /&gt;</ph> values of <ph id="ph2">&lt;see cref="F:Microsoft.Build.Framework.MessageImportance.High" /&gt;</ph>, and a build summary.</source>
          <target state="translated">最小詳細等級，顯示錯誤、警告、<ph id="ph1">&lt;see cref="T:Microsoft.Build.Framework.MessageImportance" /&gt;</ph> 值為 <ph id="ph2">&lt;see cref="F:Microsoft.Build.Framework.MessageImportance.High" /&gt;</ph> 的訊息，以及建置摘要。</target>       </trans-unit>
        <trans-unit id="108" translate="yes" xml:space="preserve" uid="F:Microsoft.Build.Framework.LoggerVerbosity.Normal">
          <source>Normal verbosity, which displays errors, warnings, messages with <ph id="ph1">&lt;see cref="T:Microsoft.Build.Framework.MessageImportance" /&gt;</ph> values of <ph id="ph2">&lt;see cref="F:Microsoft.Build.Framework.MessageImportance.High" /&gt;</ph>, some status events, and a build summary.</source>
          <target state="translated">一般詳細等級，顯示錯誤、警告、<ph id="ph1">&lt;see cref="T:Microsoft.Build.Framework.MessageImportance" /&gt;</ph> 值為 <ph id="ph2">&lt;see cref="F:Microsoft.Build.Framework.MessageImportance.High" /&gt;</ph> 的訊息、部分狀態事件，以及建置摘要。</target>       </trans-unit>
        <trans-unit id="109" translate="yes" xml:space="preserve" uid="F:Microsoft.Build.Framework.LoggerVerbosity.Quiet">
          <source>Quiet verbosity, which displays a build summary.</source>
          <target state="translated">無訊息詳細等級，顯示建置摘要。</target>       </trans-unit>
      </group>
    </body>
  </file>
</xliff>