<?xml version="1.0" encoding="utf-8"?>
<xliff xmlns="urn:oasis:names:tc:xliff:document:1.2" xmlns:xsi="http://www.w3.org/2001/XMLSchema-instance" version="1.2" xsi:schemaLocation="urn:oasis:names:tc:xliff:document:1.2 xliff-core-1.2-transitional.xsd">
  <file datatype="xml" original="SequentialWorkflowHeaderFooter.xml" source-language="en-US" target-language="zh-TW">
    <header>
      <tool tool-id="mdxliff" tool-name="mdxliff" tool-version="1.0-15c36f0" tool-company="Microsoft" />
      <xliffext:skl_file_name xmlns:xliffext="urn:microsoft:content:schema:xliffextensions">02cd5861-7ce2-4a82-b358-31f8435a0ac55aa77b7e69707fdeaa938b83a7e2a715db5003df.skl</xliffext:skl_file_name>
      <xliffext:version xmlns:xliffext="urn:microsoft:content:schema:xliffextensions">1.2</xliffext:version>
      <xliffext:ms.openlocfilehash xmlns:xliffext="urn:microsoft:content:schema:xliffextensions">5aa77b7e69707fdeaa938b83a7e2a715db5003df</xliffext:ms.openlocfilehash>
      <xliffext:ms.sourcegitcommit xmlns:xliffext="urn:microsoft:content:schema:xliffextensions">d31dc2ede16f6f7bc64e90d9f897ff54c4e3869b</xliffext:ms.sourcegitcommit>
      <xliffext:ms.lasthandoff xmlns:xliffext="urn:microsoft:content:schema:xliffextensions">04/03/2018</xliffext:ms.lasthandoff>
      <xliffext:moniker_ids xmlns:xliffext="urn:microsoft:content:schema:xliffextensions">netframework-4.5.1,netframework-4.5.2,netframework-4.5,netframework-4.6.1,netframework-4.6.2,netframework-4.6,netframework-4.7.1,netframework-4.7</xliffext:moniker_ids>
    </header>
    <body>
      <group id="content" extype="content">
        <trans-unit id="101" translate="yes" xml:space="preserve" uid="T:System.Workflow.ComponentModel.Design.SequentialWorkflowHeaderFooter">
          <source>Represents a header or footer that is associated with a <ph id="ph1">&lt;see cref="T:System.Workflow.ComponentModel.Design.SequentialWorkflowRootDesigner" /&gt;</ph>.</source>
          <target state="translated">代表與 <ph id="ph1">&lt;see cref="T:System.Workflow.ComponentModel.Design.SequentialWorkflowRootDesigner" /&gt;</ph> 相關聯的頁首或頁尾。</target>       </trans-unit>
        <trans-unit id="102" translate="yes" xml:space="preserve" extradata="MT" uid="T:System.Workflow.ComponentModel.Design.SequentialWorkflowHeaderFooter">
          <source><ph id="ph1">&lt;xref:System.Workflow.ComponentModel.Design.SequentialWorkflowHeaderFooter&gt;</ph> provides header and footer information for the <ph id="ph2">&lt;xref:System.Workflow.ComponentModel.Design.SequentialWorkflowRootDesigner&gt;</ph> when it is displayed in print preview mode.</source>
          <target state="translated"><ph id="ph1">&lt;xref:System.Workflow.ComponentModel.Design.SequentialWorkflowHeaderFooter&gt;</ph> 顯示在列印預覽模式時，為 <ph id="ph2">&lt;xref:System.Workflow.ComponentModel.Design.SequentialWorkflowRootDesigner&gt;</ph> 提供了頁首和頁尾資訊。</target>       </trans-unit>
        <trans-unit id="103" translate="yes" xml:space="preserve" extradata="MT" uid="T:System.Workflow.ComponentModel.Design.SequentialWorkflowHeaderFooter">
          <source>If provided by the workflow designer, users can configure headers and footers on the <bpt id="p1">**</bpt>Header/Footer<ept id="p1">**</ept> tab on the <bpt id="p2">**</bpt>Page Setup<ept id="p2">**</ept> dialog box.</source>
          <target state="translated">如果提供的工作流程設計工具，使用者可以設定頁首和頁尾上<bpt id="p1">**</bpt>頁首/頁尾<ept id="p1">**</ept>索引標籤上<bpt id="p2">**</bpt>版面<ept id="p2">**</ept> 對話方塊。</target>       </trans-unit>
        <trans-unit id="104" translate="yes" xml:space="preserve" uid="M:System.Workflow.ComponentModel.Design.SequentialWorkflowHeaderFooter.#ctor(System.Workflow.ComponentModel.Design.SequentialWorkflowRootDesigner,System.Boolean)">
          <source>The SequentialWorkflowRootDesigner with which the</source>
          <target state="translated">SequentialWorkflowRootDesigner，透過它，</target>       </trans-unit>
        <trans-unit id="105" translate="yes" xml:space="preserve" uid="M:System.Workflow.ComponentModel.Design.SequentialWorkflowHeaderFooter.#ctor(System.Workflow.ComponentModel.Design.SequentialWorkflowRootDesigner,System.Boolean)">
          <source><ph id="ph1">&lt;see langword="true" /&gt;</ph> to indicate that the <ph id="ph2">&lt;see cref="T:System.Workflow.ComponentModel.Design.SequentialWorkflowHeaderFooter" /&gt;</ph> is a header; <ph id="ph3">&lt;see langword="false" /&gt;</ph> to indicate that the <ph id="ph4">&lt;see cref="T:System.Workflow.ComponentModel.Design.SequentialWorkflowHeaderFooter" /&gt;</ph> is a footer.</source>
          <target state="translated"><ph id="ph1">&lt;see langword="true" /&gt;</ph> 可以判斷 <ph id="ph2">&lt;see cref="T:System.Workflow.ComponentModel.Design.SequentialWorkflowHeaderFooter" /&gt;</ph> 為頁首；<ph id="ph3">&lt;see langword="false" /&gt;</ph> 則可以判斷 <ph id="ph4">&lt;see cref="T:System.Workflow.ComponentModel.Design.SequentialWorkflowHeaderFooter" /&gt;</ph> 為頁尾。</target>       </trans-unit>
        <trans-unit id="106" translate="yes" xml:space="preserve" uid="M:System.Workflow.ComponentModel.Design.SequentialWorkflowHeaderFooter.#ctor(System.Workflow.ComponentModel.Design.SequentialWorkflowRootDesigner,System.Boolean)">
          <source>Initializes a new instance of the <ph id="ph1">&lt;see cref="T:System.Workflow.ComponentModel.Design.SequentialWorkflowHeaderFooter" /&gt;</ph> class.</source>
          <target state="translated">初始化 <ph id="ph1">&lt;see cref="T:System.Workflow.ComponentModel.Design.SequentialWorkflowHeaderFooter" /&gt;</ph> 類別的新執行個體。</target>       </trans-unit>
        <trans-unit id="107" translate="yes" xml:space="preserve" uid="P:System.Workflow.ComponentModel.Design.SequentialWorkflowHeaderFooter.AssociatedDesigner">
          <source>Gets the root designer to which the header or footer is applied.</source>
          <target state="translated">取得頁首或頁尾套用到的根目錄設計工具。</target>       </trans-unit>
        <trans-unit id="108" translate="yes" xml:space="preserve" extradata="MT" uid="P:System.Workflow.ComponentModel.Design.SequentialWorkflowHeaderFooter.AssociatedDesigner">
          <source>The <ph id="ph1">&lt;see cref="T:System.Workflow.ComponentModel.Design.SequentialWorkflowRootDesigner" /&gt;</ph> to which the <ph id="ph2">&lt;see cref="T:System.Workflow.ComponentModel.Design.SequentialWorkflowHeaderFooter" /&gt;</ph> is applied.</source>
          <target state="translated">套用到 <ph id="ph1">&lt;see cref="T:System.Workflow.ComponentModel.Design.SequentialWorkflowRootDesigner" /&gt;</ph> 的 <ph id="ph2">&lt;see cref="T:System.Workflow.ComponentModel.Design.SequentialWorkflowHeaderFooter" /&gt;</ph>。</target>       </trans-unit>
        <trans-unit id="109" translate="yes" xml:space="preserve" uid="P:System.Workflow.ComponentModel.Design.SequentialWorkflowHeaderFooter.Bounds">
          <source>Gets the bounding rectangle of the header or footer on the workflow design surface.</source>
          <target state="translated">取得工作流程設計介面上的頁首或頁尾週框。</target>       </trans-unit>
        <trans-unit id="110" translate="yes" xml:space="preserve" extradata="MT" uid="P:System.Workflow.ComponentModel.Design.SequentialWorkflowHeaderFooter.Bounds">
          <source>The <ph id="ph1">&lt;see cref="T:System.Drawing.Rectangle" /&gt;</ph> that bounds the <ph id="ph2">&lt;see cref="T:System.Workflow.ComponentModel.Design.SequentialWorkflowHeaderFooter" /&gt;</ph> on the workflow design surface.</source>
          <target state="translated">在工作流程設計介面上包圍 <ph id="ph1">&lt;see cref="T:System.Drawing.Rectangle" /&gt;</ph> 的 <ph id="ph2">&lt;see cref="T:System.Workflow.ComponentModel.Design.SequentialWorkflowHeaderFooter" /&gt;</ph>。</target>       </trans-unit>
        <trans-unit id="111" translate="yes" xml:space="preserve" uid="P:System.Workflow.ComponentModel.Design.SequentialWorkflowHeaderFooter.Image">
          <source>Gets or sets the image associated with the header or footer.</source>
          <target state="translated">取得或設定關聯於頁首或頁尾的影像。</target>       </trans-unit>
        <trans-unit id="112" translate="yes" xml:space="preserve" extradata="MT" uid="P:System.Workflow.ComponentModel.Design.SequentialWorkflowHeaderFooter.Image">
          <source>The <ph id="ph1">&lt;see cref="T:System.Drawing.Image" /&gt;</ph> to associate with the <ph id="ph2">&lt;see cref="T:System.Workflow.ComponentModel.Design.SequentialWorkflowHeaderFooter" /&gt;</ph>.</source>
          <target state="translated">要與 <ph id="ph1">&lt;see cref="T:System.Drawing.Image" /&gt;</ph> 相關聯的 <ph id="ph2">&lt;see cref="T:System.Workflow.ComponentModel.Design.SequentialWorkflowHeaderFooter" /&gt;</ph>。</target>       </trans-unit>
        <trans-unit id="113" translate="yes" xml:space="preserve" uid="P:System.Workflow.ComponentModel.Design.SequentialWorkflowHeaderFooter.ImageRectangle">
          <source>Gets the bounding rectangle for the image associated with the header or footer.</source>
          <target state="translated">取得與頁首或頁尾關聯之影像的週框。</target>       </trans-unit>
        <trans-unit id="114" translate="yes" xml:space="preserve" extradata="MT" uid="P:System.Workflow.ComponentModel.Design.SequentialWorkflowHeaderFooter.ImageRectangle">
          <source>The <ph id="ph1">&lt;see cref="T:System.Drawing.Rectangle" /&gt;</ph> that defines the bounds for the <ph id="ph2">&lt;see cref="P:System.Workflow.ComponentModel.Design.SequentialWorkflowHeaderFooter.Image" /&gt;</ph> associated with the <ph id="ph3">&lt;see cref="T:System.Workflow.ComponentModel.Design.SequentialWorkflowHeaderFooter" /&gt;</ph>.</source>
          <target state="translated"><ph id="ph1">&lt;see cref="T:System.Drawing.Rectangle" /&gt;</ph>，定義與 <ph id="ph2">&lt;see cref="P:System.Workflow.ComponentModel.Design.SequentialWorkflowHeaderFooter.Image" /&gt;</ph><ph id="ph3">&lt;see cref="T:System.Workflow.ComponentModel.Design.SequentialWorkflowHeaderFooter" /&gt;</ph>關聯之 的週框。</target>       </trans-unit>
        <trans-unit id="115" translate="yes" xml:space="preserve" extradata="MT" uid="P:System.Workflow.ComponentModel.Design.SequentialWorkflowHeaderFooter.ImageRectangle">
          <source>The following example shows how to override the <ph id="ph1">&lt;xref:System.Workflow.ComponentModel.Design.SequentialWorkflowHeaderFooter.ImageRectangle%2A&gt;</ph> property.</source>
          <target state="translated">下列範例將示範如何覆寫 <ph id="ph1">&lt;xref:System.Workflow.ComponentModel.Design.SequentialWorkflowHeaderFooter.ImageRectangle%2A&gt;</ph> 屬性。</target>       </trans-unit>
        <trans-unit id="116" translate="yes" xml:space="preserve" extradata="MT" uid="P:System.Workflow.ComponentModel.Design.SequentialWorkflowHeaderFooter.ImageRectangle">
          <source>In this example, the <ph id="ph1">&lt;xref:System.Workflow.ComponentModel.Design.SequentialWorkflowHeaderFooter.ImageRectangle%2A&gt;</ph> is calculated using the Bounds of the <ph id="ph2">&lt;xref:System.Workflow.ComponentModel.Design.SequentialWorkflowHeaderFooter&gt;</ph> to draw the image in the upper left corner of the header/footer.</source>
          <target state="translated">在此範例中，會使用 <ph id="ph1">&lt;xref:System.Workflow.ComponentModel.Design.SequentialWorkflowHeaderFooter.ImageRectangle%2A&gt;</ph><ph id="ph2">&lt;xref:System.Workflow.ComponentModel.Design.SequentialWorkflowHeaderFooter&gt;</ph>的界限來計算  以繪製頁首/頁尾左上角的影像。</target>       </trans-unit>
        <trans-unit id="117" translate="yes" xml:space="preserve" uid="M:System.Workflow.ComponentModel.Design.SequentialWorkflowHeaderFooter.OnLayout(System.Workflow.ComponentModel.Design.ActivityDesignerLayoutEventArgs)">
          <source>An <ph id="ph1">&lt;see cref="T:System.Workflow.ComponentModel.Design.ActivityDesignerLayoutEventArgs" /&gt;</ph> that contains the event data.</source>
          <target state="translated">包含事件資料的 <ph id="ph1">&lt;see cref="T:System.Workflow.ComponentModel.Design.ActivityDesignerLayoutEventArgs" /&gt;</ph>。</target>       </trans-unit>
        <trans-unit id="118" translate="yes" xml:space="preserve" uid="M:System.Workflow.ComponentModel.Design.SequentialWorkflowHeaderFooter.OnLayout(System.Workflow.ComponentModel.Design.ActivityDesignerLayoutEventArgs)">
          <source>Notifies the <ph id="ph1">&lt;see cref="T:System.Workflow.ComponentModel.Design.SequentialWorkflowHeaderFooter" /&gt;</ph> when the elements it contains are repositioned by the user.</source>
          <target state="translated">當使用者重新調整其包含項目的位置時，會告知 <ph id="ph1">&lt;see cref="T:System.Workflow.ComponentModel.Design.SequentialWorkflowHeaderFooter" /&gt;</ph>。</target>       </trans-unit>
        <trans-unit id="119" translate="yes" xml:space="preserve" uid="M:System.Workflow.ComponentModel.Design.SequentialWorkflowHeaderFooter.OnPaint(System.Workflow.ComponentModel.Design.ActivityDesignerPaintEventArgs)">
          <source>An <ph id="ph1">&lt;see cref="T:System.Workflow.ComponentModel.Design.ActivityDesignerPaintEventArgs" /&gt;</ph> that contains the event data.</source>
          <target state="translated">包含事件資料的 <ph id="ph1">&lt;see cref="T:System.Workflow.ComponentModel.Design.ActivityDesignerPaintEventArgs" /&gt;</ph>。</target>       </trans-unit>
        <trans-unit id="120" translate="yes" xml:space="preserve" uid="M:System.Workflow.ComponentModel.Design.SequentialWorkflowHeaderFooter.OnPaint(System.Workflow.ComponentModel.Design.ActivityDesignerPaintEventArgs)">
          <source>Draws the header or footer associated with the workflow root designer on the design surface.</source>
          <target state="translated">繪製與設計介面上工作流程根目錄設計工具關聯的頁首或頁尾。</target>       </trans-unit>
        <trans-unit id="121" translate="yes" xml:space="preserve" uid="M:System.Workflow.ComponentModel.Design.SequentialWorkflowHeaderFooter.OnPaint(System.Workflow.ComponentModel.Design.ActivityDesignerPaintEventArgs)">
          <source><ph id="ph1">&lt;paramref name="e" /&gt;</ph> contains a null reference (<ph id="ph2">&lt;see langword="Nothing" /&gt;</ph> in Visual Basic).</source>
          <target state="translated"><ph id="ph1">&lt;paramref name="e" /&gt;</ph> 包含 null 參考 (在 Visual Basic 中為 <ph id="ph2">&lt;see langword="Nothing" /&gt;</ph>)。</target>       </trans-unit>
        <trans-unit id="122" translate="yes" xml:space="preserve" uid="P:System.Workflow.ComponentModel.Design.SequentialWorkflowHeaderFooter.Text">
          <source>Gets or sets the text description associated with the header or footer.</source>
          <target state="translated">取得或設定關聯於頁首或頁尾的文字描述。</target>       </trans-unit>
        <trans-unit id="123" translate="yes" xml:space="preserve" extradata="MT" uid="P:System.Workflow.ComponentModel.Design.SequentialWorkflowHeaderFooter.Text">
          <source>The string that contains the text description associated with the <ph id="ph1">&lt;see cref="T:System.Workflow.ComponentModel.Design.SequentialWorkflowHeaderFooter" /&gt;</ph>.</source>
          <target state="translated">包含與 <ph id="ph1">&lt;see cref="T:System.Workflow.ComponentModel.Design.SequentialWorkflowHeaderFooter" /&gt;</ph> 關聯之文字描述的字串。</target>       </trans-unit>
        <trans-unit id="124" translate="yes" xml:space="preserve" uid="P:System.Workflow.ComponentModel.Design.SequentialWorkflowHeaderFooter.TextRectangle">
          <source>Gets the bounding rectangle for the text associated with the header or footer.</source>
          <target state="translated">取得與頁首或頁尾關聯之文字的週框。</target>       </trans-unit>
        <trans-unit id="125" translate="yes" xml:space="preserve" extradata="MT" uid="P:System.Workflow.ComponentModel.Design.SequentialWorkflowHeaderFooter.TextRectangle">
          <source>The <ph id="ph1">&lt;see cref="T:System.Drawing.Rectangle" /&gt;</ph> that defines the bounds for the <ph id="ph2">&lt;see cref="P:System.Workflow.ComponentModel.Design.SequentialWorkflowHeaderFooter.Text" /&gt;</ph> associated with the <ph id="ph3">&lt;see cref="T:System.Workflow.ComponentModel.Design.SequentialWorkflowHeaderFooter" /&gt;</ph>.</source>
          <target state="translated"><ph id="ph1">&lt;see cref="T:System.Drawing.Rectangle" /&gt;</ph>，定義與 <ph id="ph2">&lt;see cref="P:System.Workflow.ComponentModel.Design.SequentialWorkflowHeaderFooter.Text" /&gt;</ph><ph id="ph3">&lt;see cref="T:System.Workflow.ComponentModel.Design.SequentialWorkflowHeaderFooter" /&gt;</ph>關聯之 的週框。</target>       </trans-unit>
        <trans-unit id="126" translate="yes" xml:space="preserve" extradata="MT" uid="P:System.Workflow.ComponentModel.Design.SequentialWorkflowHeaderFooter.TextRectangle">
          <source>The following example shows how to override the <ph id="ph1">&lt;xref:System.Workflow.ComponentModel.Design.SequentialWorkflowHeaderFooter.TextRectangle%2A&gt;</ph> property.</source>
          <target state="translated">下列範例將示範如何覆寫 <ph id="ph1">&lt;xref:System.Workflow.ComponentModel.Design.SequentialWorkflowHeaderFooter.TextRectangle%2A&gt;</ph> 屬性。</target>       </trans-unit>
        <trans-unit id="127" translate="yes" xml:space="preserve" extradata="MT" uid="P:System.Workflow.ComponentModel.Design.SequentialWorkflowHeaderFooter.TextRectangle">
          <source>In this example, the <ph id="ph1">&lt;xref:System.Workflow.ComponentModel.Design.SequentialWorkflowHeaderFooter.TextRectangle%2A&gt;</ph> is calculated using the Bounds of the <ph id="ph2">&lt;xref:System.Workflow.ComponentModel.Design.SequentialWorkflowHeaderFooter&gt;</ph> as well as the location and size of the <ph id="ph3">&lt;xref:System.Workflow.ComponentModel.Design.SequentialWorkflowHeaderFooter.ImageRectangle%2A&gt;</ph>.</source>
          <target state="translated">在此範例中，會使用 <ph id="ph1">&lt;xref:System.Workflow.ComponentModel.Design.SequentialWorkflowHeaderFooter.TextRectangle%2A&gt;</ph> 的繫結以及 <ph id="ph2">&lt;xref:System.Workflow.ComponentModel.Design.SequentialWorkflowHeaderFooter&gt;</ph> 的位置和大小，計算 <ph id="ph3">&lt;xref:System.Workflow.ComponentModel.Design.SequentialWorkflowHeaderFooter.ImageRectangle%2A&gt;</ph>。</target>       </trans-unit>
      </group>
    </body>
  </file>
</xliff>