<?xml version="1.0" encoding="utf-8"?>
<xliff xmlns="urn:oasis:names:tc:xliff:document:1.2" xmlns:xsi="http://www.w3.org/2001/XMLSchema-instance" version="1.2" xsi:schemaLocation="urn:oasis:names:tc:xliff:document:1.2 xliff-core-1.2-transitional.xsd">
  <file datatype="xml" original="ComponentEditorForm.xml" source-language="en-US" target-language="zh-TW">
    <header>
      <tool tool-id="mdxliff" tool-name="mdxliff" tool-version="1.0-15c36f0" tool-company="Microsoft" />
      <xliffext:skl_file_name xmlns:xliffext="urn:microsoft:content:schema:xliffextensions">02cd5861-7ce2-4a82-b358-31f8435a0ac552cb70fe743b6054152608191d32d38f54ffc326.skl</xliffext:skl_file_name>
      <xliffext:version xmlns:xliffext="urn:microsoft:content:schema:xliffextensions">1.2</xliffext:version>
      <xliffext:ms.openlocfilehash xmlns:xliffext="urn:microsoft:content:schema:xliffextensions">52cb70fe743b6054152608191d32d38f54ffc326</xliffext:ms.openlocfilehash>
      <xliffext:ms.sourcegitcommit xmlns:xliffext="urn:microsoft:content:schema:xliffextensions">d31dc2ede16f6f7bc64e90d9f897ff54c4e3869b</xliffext:ms.sourcegitcommit>
      <xliffext:ms.lasthandoff xmlns:xliffext="urn:microsoft:content:schema:xliffextensions">04/03/2018</xliffext:ms.lasthandoff>
      <xliffext:moniker_ids xmlns:xliffext="urn:microsoft:content:schema:xliffextensions">netframework-4.5.1,netframework-4.5.2,netframework-4.5,netframework-4.6.1,netframework-4.6.2,netframework-4.6,netframework-4.7.1,netframework-4.7</xliffext:moniker_ids>
    </header>
    <body>
      <group id="content" extype="content">
        <trans-unit id="101" translate="yes" xml:space="preserve" uid="T:System.Windows.Forms.Design.ComponentEditorForm">
          <source>Provides a user interface for a <ph id="ph1">&lt;see cref="T:System.Windows.Forms.Design.WindowsFormsComponentEditor" /&gt;</ph>.</source>
          <target state="translated">提供 <ph id="ph1">&lt;see cref="T:System.Windows.Forms.Design.WindowsFormsComponentEditor" /&gt;</ph> 的使用者介面。</target>       </trans-unit>
        <trans-unit id="102" translate="yes" xml:space="preserve" extradata="MT" uid="T:System.Windows.Forms.Design.ComponentEditorForm">
          <source>A <ph id="ph1">&lt;xref:System.Windows.Forms.Design.ComponentEditorForm&gt;</ph> shows a view of available component editor pages along with a user interface for selection.</source>
          <target state="translated">A<ph id="ph1">&lt;xref:System.Windows.Forms.Design.ComponentEditorForm&gt;</ph>以及選取的使用者介面中顯示可用的元件編輯器頁面的檢視。</target>       </trans-unit>
        <trans-unit id="103" translate="yes" xml:space="preserve" extradata="MT" uid="T:System.Windows.Forms.Design.ComponentEditorForm">
          <source>for full access to system resources.</source>
          <target state="translated">系統資源的完整存取權。</target>       </trans-unit>
        <trans-unit id="104" translate="yes" xml:space="preserve" extradata="MT" uid="T:System.Windows.Forms.Design.ComponentEditorForm">
          <source>Demand values: <ph id="ph1">&lt;see cref="F:System.Security.Permissions.SecurityAction.LinkDemand" /&gt;</ph>, <ph id="ph2">&lt;see cref="F:System.Security.Permissions.SecurityAction.InheritanceDemand" /&gt;</ph>.</source>
          <target state="translated">要求的值： <ph id="ph1">&lt;see cref="F:System.Security.Permissions.SecurityAction.LinkDemand" /&gt;</ph>， <ph id="ph2">&lt;see cref="F:System.Security.Permissions.SecurityAction.InheritanceDemand" /&gt;</ph>。</target>       </trans-unit>
        <trans-unit id="105" translate="yes" xml:space="preserve" extradata="MT" uid="T:System.Windows.Forms.Design.ComponentEditorForm">
          <source>Associated state:</source>
          <target state="translated">相關聯的狀態：</target>       </trans-unit>
        <trans-unit id="106" translate="yes" xml:space="preserve" uid="M:System.Windows.Forms.Design.ComponentEditorForm.#ctor(System.Object,System.Type[])">
          <source>The component to be edited.</source>
          <target state="translated">要編輯的元件。</target>       </trans-unit>
        <trans-unit id="107" translate="yes" xml:space="preserve" uid="M:System.Windows.Forms.Design.ComponentEditorForm.#ctor(System.Object,System.Type[])">
          <source>The set of <ph id="ph1">&lt;see cref="T:System.Windows.Forms.Design.ComponentEditorPage" /&gt;</ph> objects to be shown in the form.</source>
          <target state="translated">要在表單中顯示的 <ph id="ph1">&lt;see cref="T:System.Windows.Forms.Design.ComponentEditorPage" /&gt;</ph> 物件集。</target>       </trans-unit>
        <trans-unit id="108" translate="yes" xml:space="preserve" uid="M:System.Windows.Forms.Design.ComponentEditorForm.#ctor(System.Object,System.Type[])">
          <source>Initializes a new instance of the <ph id="ph1">&lt;see cref="T:System.Windows.Forms.Design.ComponentEditorForm" /&gt;</ph> class.</source>
          <target state="translated">初始化 <ph id="ph1">&lt;see cref="T:System.Windows.Forms.Design.ComponentEditorForm" /&gt;</ph> 類別的新執行個體。</target>       </trans-unit>
        <trans-unit id="109" translate="yes" xml:space="preserve" uid="M:System.Windows.Forms.Design.ComponentEditorForm.#ctor(System.Object,System.Type[])">
          <source><ph id="ph1">&lt;paramref name="component" /&gt;</ph> is not an <ph id="ph2">&lt;see cref="T:System.ComponentModel.IComponent" /&gt;</ph>.</source>
          <target state="translated"><ph id="ph1">&lt;paramref name="component" /&gt;</ph> 不是 <ph id="ph2">&lt;see cref="T:System.ComponentModel.IComponent" /&gt;</ph>。</target>       </trans-unit>
        <trans-unit id="110" translate="yes" xml:space="preserve" uid="P:System.Windows.Forms.Design.ComponentEditorForm.AutoSize">
          <source>Resize the form according to the setting of <ph id="ph1">&lt;see cref="P:System.Windows.Forms.Form.AutoSizeMode" /&gt;</ph>.</source>
          <target state="translated">根據 <ph id="ph1">&lt;see cref="P:System.Windows.Forms.Form.AutoSizeMode" /&gt;</ph> 的設定調整表單大小。</target>       </trans-unit>
        <trans-unit id="111" translate="yes" xml:space="preserve" extradata="MT" uid="P:System.Windows.Forms.Design.ComponentEditorForm.AutoSize">
          <source><ph id="ph1">&lt;see langword="true" /&gt;</ph> if the form will automatically resize; <ph id="ph2">&lt;see langword="false" /&gt;</ph> if it must be manually resized.</source>
          <target state="translated">如果表單將自動調整大小，則為 <ph id="ph1">&lt;see langword="true" /&gt;</ph>；如果必須手動調整大小，則為 <ph id="ph2">&lt;see langword="false" /&gt;</ph>。</target>       </trans-unit>
        <trans-unit id="112" translate="yes" xml:space="preserve" uid="E:System.Windows.Forms.Design.ComponentEditorForm.AutoSizeChanged">
          <source>Occurs when the <ph id="ph1">&lt;see cref="P:System.Windows.Forms.Form.AutoSize" /&gt;</ph> property changes.</source>
          <target state="translated">發生於 <ph id="ph1">&lt;see cref="P:System.Windows.Forms.Form.AutoSize" /&gt;</ph> 屬性變更時。</target>       </trans-unit>
        <trans-unit id="113" translate="yes" xml:space="preserve" uid="M:System.Windows.Forms.Design.ComponentEditorForm.OnActivated(System.EventArgs)">
          <source>An <ph id="ph1">&lt;see cref="T:System.EventArgs" /&gt;</ph> that contains the event data.</source>
          <target state="translated">包含事件資料的 <ph id="ph1">&lt;see cref="T:System.EventArgs" /&gt;</ph>。</target>       </trans-unit>
        <trans-unit id="114" translate="yes" xml:space="preserve" uid="M:System.Windows.Forms.Design.ComponentEditorForm.OnActivated(System.EventArgs)">
          <source>Raises the <ph id="ph1">&lt;see cref="E:System.Windows.Forms.Form.Activated" /&gt;</ph> event.</source>
          <target state="translated">引發 <ph id="ph1">&lt;see cref="E:System.Windows.Forms.Form.Activated" /&gt;</ph> 事件。</target>       </trans-unit>
        <trans-unit id="115" translate="yes" xml:space="preserve" extradata="MT" uid="M:System.Windows.Forms.Design.ComponentEditorForm.OnActivated(System.EventArgs)">
          <source>The first time the <ph id="ph1">&lt;xref:System.Windows.Forms.Design.ComponentEditorForm.OnActivated%2A&gt;</ph> method is executed, it shows the first component editor page in the list.</source>
          <target state="translated">第一次<ph id="ph1">&lt;xref:System.Windows.Forms.Design.ComponentEditorForm.OnActivated%2A&gt;</ph>執行方法，它會顯示在清單中的第一個元件編輯器頁面。</target>       </trans-unit>
        <trans-unit id="116" translate="yes" xml:space="preserve" extradata="MT" uid="M:System.Windows.Forms.Design.ComponentEditorForm.OnActivated(System.EventArgs)">
          <source>Raising an event invokes the event handler through a delegate.</source>
          <target state="translated">引發事件會透過委派叫用此事件處理常式。</target>       </trans-unit>
        <trans-unit id="117" translate="yes" xml:space="preserve" extradata="MT" uid="M:System.Windows.Forms.Design.ComponentEditorForm.OnActivated(System.EventArgs)">
          <source>For more information, see <bpt id="p1">[</bpt>Handling and Raising Events<ept id="p1">](~/docs/standard/events/index.md)</ept>.</source>
          <target state="translated">如需詳細資訊，請參閱<bpt id="p1">[</bpt>處理和引發事件<ept id="p1">](~/docs/standard/events/index.md)</ept>。</target>       </trans-unit>
        <trans-unit id="118" translate="yes" xml:space="preserve" extradata="MT" uid="M:System.Windows.Forms.Design.ComponentEditorForm.OnActivated(System.EventArgs)">
          <source>The <ph id="ph1">&lt;xref:System.Windows.Forms.Design.ComponentEditorForm.OnActivated%2A&gt;</ph> method also allows derived classes to handle the event without attaching a delegate.</source>
          <target state="translated"><ph id="ph1">&lt;xref:System.Windows.Forms.Design.ComponentEditorForm.OnActivated%2A&gt;</ph> 方法也允許衍生類別處理事件，而不用附加委派。</target>       </trans-unit>
        <trans-unit id="119" translate="yes" xml:space="preserve" extradata="MT" uid="M:System.Windows.Forms.Design.ComponentEditorForm.OnActivated(System.EventArgs)">
          <source>This is the preferred technique for handling the event in a derived class.</source>
          <target state="translated">這是在衍生類別中處理事件的慣用技巧。</target>       </trans-unit>
        <trans-unit id="120" translate="yes" xml:space="preserve" extradata="MT" uid="M:System.Windows.Forms.Design.ComponentEditorForm.OnActivated(System.EventArgs)">
          <source>When overriding <ph id="ph1">&lt;see cref="M:System.Windows.Forms.Design.ComponentEditorForm.OnActivated(System.EventArgs)" /&gt;</ph> in a derived class, be sure to call the base class’s <ph id="ph2">&lt;see cref="M:System.Windows.Forms.Design.ComponentEditorForm.OnActivated(System.EventArgs)" /&gt;</ph> method so that registered delegates receive the event.</source>
          <target state="translated">在覆寫<ph id="ph1">&lt;see cref="M:System.Windows.Forms.Design.ComponentEditorForm.OnActivated(System.EventArgs)" /&gt;</ph>在衍生類別中，請務必呼叫基底類別的<ph id="ph2">&lt;see cref="M:System.Windows.Forms.Design.ComponentEditorForm.OnActivated(System.EventArgs)" /&gt;</ph>方法，使已註冊的委派能接收到事件。</target>       </trans-unit>
        <trans-unit id="121" translate="yes" xml:space="preserve" uid="M:System.Windows.Forms.Design.ComponentEditorForm.OnHelpRequested(System.Windows.Forms.HelpEventArgs)">
          <source>A <ph id="ph1">&lt;see cref="T:System.Windows.Forms.HelpEventArgs" /&gt;</ph> that contains the event data.</source>
          <target state="translated"><ph id="ph1">&lt;see cref="T:System.Windows.Forms.HelpEventArgs" /&gt;</ph>，其中包含事件資料。</target>       </trans-unit>
        <trans-unit id="122" translate="yes" xml:space="preserve" uid="M:System.Windows.Forms.Design.ComponentEditorForm.OnHelpRequested(System.Windows.Forms.HelpEventArgs)">
          <source>Raises the <ph id="ph1">&lt;see cref="E:System.Windows.Forms.Control.HelpRequested" /&gt;</ph> event.</source>
          <target state="translated">引發 <ph id="ph1">&lt;see cref="E:System.Windows.Forms.Control.HelpRequested" /&gt;</ph> 事件。</target>       </trans-unit>
        <trans-unit id="123" translate="yes" xml:space="preserve" extradata="MT" uid="M:System.Windows.Forms.Design.ComponentEditorForm.OnHelpRequested(System.Windows.Forms.HelpEventArgs)">
          <source>The <ph id="ph1">&lt;xref:System.Windows.Forms.Design.ComponentEditorForm.OnHelpRequested%2A&gt;</ph> method shows the Help page that is associated with the component editor page, if there is one.</source>
          <target state="translated"><ph id="ph1">&lt;xref:System.Windows.Forms.Design.ComponentEditorForm.OnHelpRequested%2A&gt;</ph>方法顯示的說明頁的相關聯的元件編輯器頁面上，如果有的話。</target>       </trans-unit>
        <trans-unit id="124" translate="yes" xml:space="preserve" extradata="MT" uid="M:System.Windows.Forms.Design.ComponentEditorForm.OnHelpRequested(System.Windows.Forms.HelpEventArgs)">
          <source>Raising an event invokes the event handler through a delegate.</source>
          <target state="translated">引發事件會透過委派叫用此事件處理常式。</target>       </trans-unit>
        <trans-unit id="125" translate="yes" xml:space="preserve" extradata="MT" uid="M:System.Windows.Forms.Design.ComponentEditorForm.OnHelpRequested(System.Windows.Forms.HelpEventArgs)">
          <source>For more information, see <bpt id="p1">[</bpt>Handling and Raising Events<ept id="p1">](~/docs/standard/events/index.md)</ept>.</source>
          <target state="translated">如需詳細資訊，請參閱<bpt id="p1">[</bpt>處理和引發事件<ept id="p1">](~/docs/standard/events/index.md)</ept>。</target>       </trans-unit>
        <trans-unit id="126" translate="yes" xml:space="preserve" extradata="MT" uid="M:System.Windows.Forms.Design.ComponentEditorForm.OnHelpRequested(System.Windows.Forms.HelpEventArgs)">
          <source>The <ph id="ph1">&lt;xref:System.Windows.Forms.Design.ComponentEditorForm.OnHelpRequested%2A&gt;</ph> method also allows derived classes to handle the event without attaching a delegate.</source>
          <target state="translated"><ph id="ph1">&lt;xref:System.Windows.Forms.Design.ComponentEditorForm.OnHelpRequested%2A&gt;</ph> 方法也允許衍生類別處理事件，而不用附加委派。</target>       </trans-unit>
        <trans-unit id="127" translate="yes" xml:space="preserve" extradata="MT" uid="M:System.Windows.Forms.Design.ComponentEditorForm.OnHelpRequested(System.Windows.Forms.HelpEventArgs)">
          <source>This is the preferred technique for handling the event in a derived class.</source>
          <target state="translated">這是在衍生類別中處理事件的慣用技巧。</target>       </trans-unit>
        <trans-unit id="128" translate="yes" xml:space="preserve" extradata="MT" uid="M:System.Windows.Forms.Design.ComponentEditorForm.OnHelpRequested(System.Windows.Forms.HelpEventArgs)">
          <source>When overriding <ph id="ph1">&lt;see cref="M:System.Windows.Forms.Design.ComponentEditorForm.OnHelpRequested(System.Windows.Forms.HelpEventArgs)" /&gt;</ph> in a derived class, be sure to call the base class’s <ph id="ph2">&lt;see cref="M:System.Windows.Forms.Design.ComponentEditorForm.OnHelpRequested(System.Windows.Forms.HelpEventArgs)" /&gt;</ph> method so that registered delegates receive the event.</source>
          <target state="translated">在覆寫<ph id="ph1">&lt;see cref="M:System.Windows.Forms.Design.ComponentEditorForm.OnHelpRequested(System.Windows.Forms.HelpEventArgs)" /&gt;</ph>在衍生類別中，請務必呼叫基底類別的<ph id="ph2">&lt;see cref="M:System.Windows.Forms.Design.ComponentEditorForm.OnHelpRequested(System.Windows.Forms.HelpEventArgs)" /&gt;</ph>方法，使已註冊的委派能接收到事件。</target>       </trans-unit>
        <trans-unit id="129" translate="yes" xml:space="preserve" uid="M:System.Windows.Forms.Design.ComponentEditorForm.OnSelChangeSelector(System.Object,System.Windows.Forms.TreeViewEventArgs)">
          <source>The source of the event.</source>
          <target state="translated">事件的來源。</target>       </trans-unit>
        <trans-unit id="130" translate="yes" xml:space="preserve" uid="M:System.Windows.Forms.Design.ComponentEditorForm.OnSelChangeSelector(System.Object,System.Windows.Forms.TreeViewEventArgs)">
          <source>A <ph id="ph1">&lt;see cref="T:System.Windows.Forms.TreeViewEventArgs" /&gt;</ph> that contains the event data.</source>
          <target state="translated"><ph id="ph1">&lt;see cref="T:System.Windows.Forms.TreeViewEventArgs" /&gt;</ph>，其中包含事件資料。</target>       </trans-unit>
        <trans-unit id="131" translate="yes" xml:space="preserve" uid="M:System.Windows.Forms.Design.ComponentEditorForm.OnSelChangeSelector(System.Object,System.Windows.Forms.TreeViewEventArgs)">
          <source>Switches between component editor pages.</source>
          <target state="translated">在元件編輯器頁面之間切換。</target>       </trans-unit>
        <trans-unit id="132" translate="yes" xml:space="preserve" uid="M:System.Windows.Forms.Design.ComponentEditorForm.OnSelChangeSelector(System.Object,System.Windows.Forms.TreeViewEventArgs)">
          <source>A designer file is checked into source code control and cannot be changed.</source>
          <target state="translated">設計工具檔已簽入原始程式碼控制，且無法變更。</target>       </trans-unit>
        <trans-unit id="133" translate="yes" xml:space="preserve" uid="M:System.Windows.Forms.Design.ComponentEditorForm.PreProcessMessage(System.Windows.Forms.Message@)">
          <source>A <ph id="ph1">&lt;see cref="T:System.Windows.Forms.Message" /&gt;</ph> that specifies the message to preprocess.</source>
          <target state="translated"><ph id="ph1">&lt;see cref="T:System.Windows.Forms.Message" /&gt;</ph>，指定要前置處理的訊息。</target>       </trans-unit>
        <trans-unit id="134" translate="yes" xml:space="preserve" uid="M:System.Windows.Forms.Design.ComponentEditorForm.PreProcessMessage(System.Windows.Forms.Message@)">
          <source>Provides a method to override in order to preprocess input messages before they are dispatched.</source>
          <target state="translated">提供一種覆寫方法，在分派輸入訊息前先進行前置處理。</target>       </trans-unit>
        <trans-unit id="135" translate="yes" xml:space="preserve" uid="M:System.Windows.Forms.Design.ComponentEditorForm.PreProcessMessage(System.Windows.Forms.Message@)">
          <source><ph id="ph1">&lt;see langword="true" /&gt;</ph> if the specified message is for a component editor page; otherwise, <ph id="ph2">&lt;see langword="false" /&gt;</ph>.</source>
          <target state="translated">如果指定的訊息是供元件編輯器頁面使用，則為 <ph id="ph1">&lt;see langword="true" /&gt;</ph>，否則為 <ph id="ph2">&lt;see langword="false" /&gt;</ph>。</target>       </trans-unit>
        <trans-unit id="136" translate="yes" xml:space="preserve" extradata="MT" uid="M:System.Windows.Forms.Design.ComponentEditorForm.PreProcessMessage(System.Windows.Forms.Message@)">
          <source><ph id="ph1">&lt;xref:System.Windows.Forms.Design.ComponentEditorForm.PreProcessMessage%2A&gt;</ph> is called by the application's message loop to preprocess input messages before they are dispatched.</source>
          <target state="translated"><ph id="ph1">&lt;xref:System.Windows.Forms.Design.ComponentEditorForm.PreProcessMessage%2A&gt;</ph> 會呼叫預先處理輸入的訊息，再分派這些應用程式的訊息迴圈。</target>       </trans-unit>
        <trans-unit id="137" translate="yes" xml:space="preserve" extradata="MT" uid="M:System.Windows.Forms.Design.ComponentEditorForm.PreProcessMessage(System.Windows.Forms.Message@)">
          <source>for full access to system resources.</source>
          <target state="translated">系統資源的完整存取權。</target>       </trans-unit>
        <trans-unit id="138" translate="yes" xml:space="preserve" extradata="MT" uid="M:System.Windows.Forms.Design.ComponentEditorForm.PreProcessMessage(System.Windows.Forms.Message@)">
          <source>Demand values: <ph id="ph1">&lt;see cref="F:System.Security.Permissions.SecurityAction.LinkDemand" /&gt;</ph>, <ph id="ph2">&lt;see cref="F:System.Security.Permissions.SecurityAction.InheritanceDemand" /&gt;</ph>.</source>
          <target state="translated">要求的值： <ph id="ph1">&lt;see cref="F:System.Security.Permissions.SecurityAction.LinkDemand" /&gt;</ph>， <ph id="ph2">&lt;see cref="F:System.Security.Permissions.SecurityAction.InheritanceDemand" /&gt;</ph>。</target>       </trans-unit>
        <trans-unit id="139" translate="yes" xml:space="preserve" extradata="MT" uid="M:System.Windows.Forms.Design.ComponentEditorForm.PreProcessMessage(System.Windows.Forms.Message@)">
          <source>Associated state:</source>
          <target state="translated">相關聯的狀態：</target>       </trans-unit>
        <trans-unit id="140" translate="yes" xml:space="preserve" extradata="MT" uid="M:System.Windows.Forms.Design.ComponentEditorForm.PreProcessMessage(System.Windows.Forms.Message@)">
          <source>for access to unmanaged code.</source>
          <target state="translated">用於存取 unmanaged 程式碼。</target>       </trans-unit>
        <trans-unit id="141" translate="yes" xml:space="preserve" extradata="MT" uid="M:System.Windows.Forms.Design.ComponentEditorForm.PreProcessMessage(System.Windows.Forms.Message@)">
          <source>Associated enumeration: <ph id="ph1">&lt;see cref="F:System.Security.Permissions.SecurityPermissionFlag.UnmanagedCode" /&gt;</ph></source>
          <target state="translated">相關聯的列舉型別： <ph id="ph1">&lt;see cref="F:System.Security.Permissions.SecurityPermissionFlag.UnmanagedCode" /&gt;</ph></target>       </trans-unit>
        <trans-unit id="142" translate="yes" xml:space="preserve" uid="T:System.Windows.Forms.Design.ComponentEditorForm">
          <source>Shows the form.</source>
          <target state="translated">顯示表單。</target>       </trans-unit>
        <trans-unit id="143" translate="yes" xml:space="preserve" uid="T:System.Windows.Forms.Design.ComponentEditorForm">
          <source>The form will have no owner window.</source>
          <target state="translated">表單將不會有主控視窗。</target>       </trans-unit>
        <trans-unit id="144" translate="yes" xml:space="preserve" uid="M:System.Windows.Forms.Design.ComponentEditorForm.ShowForm">
          <source>Shows the form.</source>
          <target state="translated">顯示表單。</target>       </trans-unit>
        <trans-unit id="145" translate="yes" xml:space="preserve" uid="M:System.Windows.Forms.Design.ComponentEditorForm.ShowForm">
          <source>The form will have no owner window.</source>
          <target state="translated">表單將不會有主控視窗。</target>       </trans-unit>
        <trans-unit id="146" translate="yes" xml:space="preserve" uid="M:System.Windows.Forms.Design.ComponentEditorForm.ShowForm">
          <source>One of the <ph id="ph1">&lt;see cref="T:System.Windows.Forms.DialogResult" /&gt;</ph> values indicating the result code returned from the dialog box.</source>
          <target state="translated">其中一個 <ph id="ph1">&lt;see cref="T:System.Windows.Forms.DialogResult" /&gt;</ph> 值，表示從對話方塊傳回的結果代碼。</target>       </trans-unit>
        <trans-unit id="147" translate="yes" xml:space="preserve" uid="M:System.Windows.Forms.Design.ComponentEditorForm.ShowForm(System.Int32)">
          <source>The index of the page to show.</source>
          <target state="translated">要顯示的頁面的索引。</target>       </trans-unit>
        <trans-unit id="148" translate="yes" xml:space="preserve" uid="M:System.Windows.Forms.Design.ComponentEditorForm.ShowForm(System.Int32)">
          <source>Shows the specified page of the specified form.</source>
          <target state="translated">顯示指定表單中指定的頁面。</target>       </trans-unit>
        <trans-unit id="149" translate="yes" xml:space="preserve" uid="M:System.Windows.Forms.Design.ComponentEditorForm.ShowForm(System.Int32)">
          <source>The form will have no owner window.</source>
          <target state="translated">表單將不會有主控視窗。</target>       </trans-unit>
        <trans-unit id="150" translate="yes" xml:space="preserve" uid="M:System.Windows.Forms.Design.ComponentEditorForm.ShowForm(System.Int32)">
          <source>One of the <ph id="ph1">&lt;see cref="T:System.Windows.Forms.DialogResult" /&gt;</ph> values indicating the result code returned from the dialog box.</source>
          <target state="translated">其中一個 <ph id="ph1">&lt;see cref="T:System.Windows.Forms.DialogResult" /&gt;</ph> 值，表示從對話方塊傳回的結果代碼。</target>       </trans-unit>
        <trans-unit id="151" translate="yes" xml:space="preserve" uid="M:System.Windows.Forms.Design.ComponentEditorForm.ShowForm(System.Windows.Forms.IWin32Window)">
          <source>The <ph id="ph1">&lt;see cref="T:System.Windows.Forms.IWin32Window" /&gt;</ph> to own the dialog.</source>
          <target state="translated">要擁有對話方塊的 <ph id="ph1">&lt;see cref="T:System.Windows.Forms.IWin32Window" /&gt;</ph>。</target>       </trans-unit>
        <trans-unit id="152" translate="yes" xml:space="preserve" uid="M:System.Windows.Forms.Design.ComponentEditorForm.ShowForm(System.Windows.Forms.IWin32Window)">
          <source>Shows the form with the specified owner.</source>
          <target state="translated">顯示具有指定的擁有人的表單。</target>       </trans-unit>
        <trans-unit id="153" translate="yes" xml:space="preserve" uid="M:System.Windows.Forms.Design.ComponentEditorForm.ShowForm(System.Windows.Forms.IWin32Window)">
          <source>One of the <ph id="ph1">&lt;see cref="T:System.Windows.Forms.DialogResult" /&gt;</ph> values indicating the result code returned from the dialog box.</source>
          <target state="translated">其中一個 <ph id="ph1">&lt;see cref="T:System.Windows.Forms.DialogResult" /&gt;</ph> 值，表示從對話方塊傳回的結果代碼。</target>       </trans-unit>
        <trans-unit id="154" translate="yes" xml:space="preserve" uid="M:System.Windows.Forms.Design.ComponentEditorForm.ShowForm(System.Windows.Forms.IWin32Window,System.Int32)">
          <source>The <ph id="ph1">&lt;see cref="T:System.Windows.Forms.IWin32Window" /&gt;</ph> to own the dialog.</source>
          <target state="translated">要擁有對話方塊的 <ph id="ph1">&lt;see cref="T:System.Windows.Forms.IWin32Window" /&gt;</ph>。</target>       </trans-unit>
        <trans-unit id="155" translate="yes" xml:space="preserve" uid="M:System.Windows.Forms.Design.ComponentEditorForm.ShowForm(System.Windows.Forms.IWin32Window,System.Int32)">
          <source>The index of the page to show.</source>
          <target state="translated">要顯示的頁面的索引。</target>       </trans-unit>
        <trans-unit id="156" translate="yes" xml:space="preserve" uid="M:System.Windows.Forms.Design.ComponentEditorForm.ShowForm(System.Windows.Forms.IWin32Window,System.Int32)">
          <source>Shows the form and the specified page with the specified owner.</source>
          <target state="translated">顯示具有指定擁有人的表單和指定的頁面。</target>       </trans-unit>
        <trans-unit id="157" translate="yes" xml:space="preserve" uid="M:System.Windows.Forms.Design.ComponentEditorForm.ShowForm(System.Windows.Forms.IWin32Window,System.Int32)">
          <source>One of the <ph id="ph1">&lt;see cref="T:System.Windows.Forms.DialogResult" /&gt;</ph> values indicating the result code returned from the dialog box.</source>
          <target state="translated">其中一個 <ph id="ph1">&lt;see cref="T:System.Windows.Forms.DialogResult" /&gt;</ph> 值，表示從對話方塊傳回的結果代碼。</target>       </trans-unit>
      </group>
    </body>
  </file>
</xliff>