<?xml version="1.0" encoding="utf-8"?>
<xliff xmlns="urn:oasis:names:tc:xliff:document:1.2" xmlns:xsi="http://www.w3.org/2001/XMLSchema-instance" version="1.2" xsi:schemaLocation="urn:oasis:names:tc:xliff:document:1.2 xliff-core-1.2-transitional.xsd">
  <file datatype="xml" original="ISymbolDocument.xml" source-language="en-US" target-language="zh-TW">
    <header>
      <tool tool-id="mdxliff" tool-name="mdxliff" tool-version="1.0-15c36f0" tool-company="Microsoft" />
      <xliffext:skl_file_name xmlns:xliffext="urn:microsoft:content:schema:xliffextensions">02cd5861-7ce2-4a82-b358-31f8435a0ac5ca5744d492a767ec8c091e47e7ff5d5ed2b497f5.skl</xliffext:skl_file_name>
      <xliffext:version xmlns:xliffext="urn:microsoft:content:schema:xliffextensions">1.2</xliffext:version>
      <xliffext:ms.openlocfilehash xmlns:xliffext="urn:microsoft:content:schema:xliffextensions">ca5744d492a767ec8c091e47e7ff5d5ed2b497f5</xliffext:ms.openlocfilehash>
      <xliffext:ms.sourcegitcommit xmlns:xliffext="urn:microsoft:content:schema:xliffextensions">d31dc2ede16f6f7bc64e90d9f897ff54c4e3869b</xliffext:ms.sourcegitcommit>
      <xliffext:ms.lasthandoff xmlns:xliffext="urn:microsoft:content:schema:xliffextensions">04/03/2018</xliffext:ms.lasthandoff>
      <xliffext:moniker_ids xmlns:xliffext="urn:microsoft:content:schema:xliffextensions">netcore-2.0,netcore-2.1,netframework-4.5.1,netframework-4.5.2,netframework-4.5,netframework-4.6.1,netframework-4.6.2,netframework-4.6,netframework-4.7.1,netframework-4.7,netstandard-2.0,xamarinandroid-7.1,xamarinios-10.8,xamarinmac-3.0</xliffext:moniker_ids>
    </header>
    <body>
      <group id="content" extype="content">
        <trans-unit id="101" translate="yes" xml:space="preserve" uid="T:System.Diagnostics.SymbolStore.ISymbolDocument">
          <source>Represents a document referenced by a symbol store.</source>
          <target state="translated">代表符號存放區所參考的文件。</target>       </trans-unit>
        <trans-unit id="102" translate="yes" xml:space="preserve" extradata="MT" uid="T:System.Diagnostics.SymbolStore.ISymbolDocument">
          <source>A document is defined by a URL and a document type GUID.</source>
          <target state="translated">文件 URL 和文件類型 GUID 所定義。</target>       </trans-unit>
        <trans-unit id="103" translate="yes" xml:space="preserve" extradata="MT" uid="T:System.Diagnostics.SymbolStore.ISymbolDocument">
          <source>Using the document type GUID and the URL, you can locate the document.</source>
          <target state="translated">使用文件類型的 GUID 和 URL，您可以找出文件。</target>       </trans-unit>
        <trans-unit id="104" translate="yes" xml:space="preserve" extradata="MT" uid="T:System.Diagnostics.SymbolStore.ISymbolDocument">
          <source>You can optionally store document source in the symbol store.</source>
          <target state="translated">您可以選擇性地儲存文件來源，在符號存放區中。</target>       </trans-unit>
        <trans-unit id="105" translate="yes" xml:space="preserve" extradata="MT" uid="T:System.Diagnostics.SymbolStore.ISymbolDocument">
          <source>This interface also provides access to that source, if present.</source>
          <target state="translated">此介面也會提供存取該來源中，如果有的話。</target>       </trans-unit>
        <trans-unit id="106" translate="yes" xml:space="preserve" extradata="MT" uid="T:System.Diagnostics.SymbolStore.ISymbolDocument">
          <source>This interface is the managed counterpart of the <ph id="ph1">`ISymUnmanagedDocument`</ph> interface, one of the unmanaged symbol store interfaces that provide an alternative way to read and write debug symbol information.</source>
          <target state="translated">這個介面是 managed 對應項目<ph id="ph1">`ISymUnmanagedDocument`</ph>介面提供的替代方法來讀取和寫入偵錯符號資訊的 unmanaged 的符號存放區介面之一。</target>       </trans-unit>
        <trans-unit id="107" translate="yes" xml:space="preserve" uid="P:System.Diagnostics.SymbolStore.ISymbolDocument.CheckSumAlgorithmId">
          <source>Gets the checksum algorithm identifier.</source>
          <target state="translated">取得總和檢查碼演算法識別項。</target>       </trans-unit>
        <trans-unit id="108" translate="yes" xml:space="preserve" extradata="MT" uid="P:System.Diagnostics.SymbolStore.ISymbolDocument.CheckSumAlgorithmId">
          <source>A GUID identifying the checksum algorithm.</source>
          <target state="translated">識別總和檢查碼演算法的 GUID。</target>       </trans-unit>
        <trans-unit id="109" translate="yes" xml:space="preserve" extradata="MT" uid="P:System.Diagnostics.SymbolStore.ISymbolDocument.CheckSumAlgorithmId">
          <source>The value is all zeros, if there is no checksum.</source>
          <target state="translated">如果沒有任何總和檢查碼，該值會全部為零。</target>       </trans-unit>
        <trans-unit id="110" translate="yes" xml:space="preserve" uid="P:System.Diagnostics.SymbolStore.ISymbolDocument.DocumentType">
          <source>Gets the type of the current document.</source>
          <target state="translated">取得目前文件的類型。</target>       </trans-unit>
        <trans-unit id="111" translate="yes" xml:space="preserve" extradata="MT" uid="P:System.Diagnostics.SymbolStore.ISymbolDocument.DocumentType">
          <source>The type of the current document.</source>
          <target state="translated">目前文件的類型。</target>       </trans-unit>
        <trans-unit id="112" translate="yes" xml:space="preserve" uid="M:System.Diagnostics.SymbolStore.ISymbolDocument.FindClosestLine(System.Int32)">
          <source>The specified line in the document.</source>
          <target state="translated">文件中的指定行。</target>       </trans-unit>
        <trans-unit id="113" translate="yes" xml:space="preserve" uid="M:System.Diagnostics.SymbolStore.ISymbolDocument.FindClosestLine(System.Int32)">
          <source>Returns the closest line that is a sequence point, given a line in the current document that might or might not be a sequence point.</source>
          <target state="translated">在目前文件中不一定是序列點的行之情況下，傳回是序列點的最接近一行。</target>       </trans-unit>
        <trans-unit id="114" translate="yes" xml:space="preserve" uid="M:System.Diagnostics.SymbolStore.ISymbolDocument.FindClosestLine(System.Int32)">
          <source>The closest line that is a sequence point.</source>
          <target state="translated">最接近的一行 (也就是序列點)。</target>       </trans-unit>
        <trans-unit id="115" translate="yes" xml:space="preserve" uid="M:System.Diagnostics.SymbolStore.ISymbolDocument.GetCheckSum">
          <source>Gets the checksum.</source>
          <target state="translated">取得總和檢查碼。</target>       </trans-unit>
        <trans-unit id="116" translate="yes" xml:space="preserve" uid="M:System.Diagnostics.SymbolStore.ISymbolDocument.GetCheckSum">
          <source>The checksum.</source>
          <target state="translated">總和檢查碼。</target>       </trans-unit>
        <trans-unit id="117" translate="yes" xml:space="preserve" uid="M:System.Diagnostics.SymbolStore.ISymbolDocument.GetSourceRange(System.Int32,System.Int32,System.Int32,System.Int32)">
          <source>The starting line in the current document.</source>
          <target state="translated">目前文件中的起始行。</target>       </trans-unit>
        <trans-unit id="118" translate="yes" xml:space="preserve" uid="M:System.Diagnostics.SymbolStore.ISymbolDocument.GetSourceRange(System.Int32,System.Int32,System.Int32,System.Int32)">
          <source>The starting column in the current document.</source>
          <target state="translated">目前文件中的起始欄。</target>       </trans-unit>
        <trans-unit id="119" translate="yes" xml:space="preserve" uid="M:System.Diagnostics.SymbolStore.ISymbolDocument.GetSourceRange(System.Int32,System.Int32,System.Int32,System.Int32)">
          <source>The ending line in the current document.</source>
          <target state="translated">目前文件中的結束行。</target>       </trans-unit>
        <trans-unit id="120" translate="yes" xml:space="preserve" uid="M:System.Diagnostics.SymbolStore.ISymbolDocument.GetSourceRange(System.Int32,System.Int32,System.Int32,System.Int32)">
          <source>The ending column in the current document.</source>
          <target state="translated">目前文件中的結束欄。</target>       </trans-unit>
        <trans-unit id="121" translate="yes" xml:space="preserve" uid="M:System.Diagnostics.SymbolStore.ISymbolDocument.GetSourceRange(System.Int32,System.Int32,System.Int32,System.Int32)">
          <source>Gets the embedded document source for the specified range.</source>
          <target state="translated">取得指定範圍的內嵌文件來源。</target>       </trans-unit>
        <trans-unit id="122" translate="yes" xml:space="preserve" uid="M:System.Diagnostics.SymbolStore.ISymbolDocument.GetSourceRange(System.Int32,System.Int32,System.Int32,System.Int32)">
          <source>The document source for the specified range.</source>
          <target state="translated">指定範圍的文件來源。</target>       </trans-unit>
        <trans-unit id="123" translate="yes" xml:space="preserve" uid="P:System.Diagnostics.SymbolStore.ISymbolDocument.HasEmbeddedSource">
          <source>Checks whether the current document is stored in the symbol store.</source>
          <target state="translated">檢查目前文件是否存放在符號存放區中。</target>       </trans-unit>
        <trans-unit id="124" translate="yes" xml:space="preserve" extradata="MT" uid="P:System.Diagnostics.SymbolStore.ISymbolDocument.HasEmbeddedSource">
          <source><ph id="ph1">&lt;see langword="true" /&gt;</ph> if the current document is stored in the symbol store; otherwise, <ph id="ph2">&lt;see langword="false" /&gt;</ph>.</source>
          <target state="translated">如果目前文件是存放在符號存放區中，則為 <ph id="ph1">&lt;see langword="true" /&gt;</ph>，否則為 <ph id="ph2">&lt;see langword="false" /&gt;</ph>。</target>       </trans-unit>
        <trans-unit id="125" translate="yes" xml:space="preserve" uid="P:System.Diagnostics.SymbolStore.ISymbolDocument.Language">
          <source>Gets the language of the current document.</source>
          <target state="translated">取得目前文件的語言。</target>       </trans-unit>
        <trans-unit id="126" translate="yes" xml:space="preserve" extradata="MT" uid="P:System.Diagnostics.SymbolStore.ISymbolDocument.Language">
          <source>The language of the current document.</source>
          <target state="translated">目前文件的語言。</target>       </trans-unit>
        <trans-unit id="127" translate="yes" xml:space="preserve" uid="P:System.Diagnostics.SymbolStore.ISymbolDocument.LanguageVendor">
          <source>Gets the language vendor of the current document.</source>
          <target state="translated">取得目前文件的語言廠商。</target>       </trans-unit>
        <trans-unit id="128" translate="yes" xml:space="preserve" extradata="MT" uid="P:System.Diagnostics.SymbolStore.ISymbolDocument.LanguageVendor">
          <source>The language vendor of the current document.</source>
          <target state="translated">目前文件的語言廠商。</target>       </trans-unit>
        <trans-unit id="129" translate="yes" xml:space="preserve" uid="P:System.Diagnostics.SymbolStore.ISymbolDocument.SourceLength">
          <source>Gets the length, in bytes, of the embedded source.</source>
          <target state="translated">取得內嵌來源的長度 (以位元組為單位)。</target>       </trans-unit>
        <trans-unit id="130" translate="yes" xml:space="preserve" extradata="MT" uid="P:System.Diagnostics.SymbolStore.ISymbolDocument.SourceLength">
          <source>The source length of the current document.</source>
          <target state="translated">目前文件的來源長度。</target>       </trans-unit>
        <trans-unit id="131" translate="yes" xml:space="preserve" uid="P:System.Diagnostics.SymbolStore.ISymbolDocument.URL">
          <source>Gets the URL of the current document.</source>
          <target state="translated">取得目前文件的 URL。</target>       </trans-unit>
        <trans-unit id="132" translate="yes" xml:space="preserve" extradata="MT" uid="P:System.Diagnostics.SymbolStore.ISymbolDocument.URL">
          <source>The URL of the current document.</source>
          <target state="translated">目前文件的 URL。</target>       </trans-unit>
      </group>
    </body>
  </file>
</xliff>